sqlgrants/__init__.py
sqlgrants/base.py
sqlgrants/exceptions.py
sqlgrants/mysql/__init__.py
sqlgrants/mysql/grants.py
sqlgrants/mysql/mysql.py
tests/__init__.py
tests/base.py
tests/exceptions.py
python_SQLGrants-1.1.2.dist-info/LICENSE
python_SQLGrants-1.1.2.dist-info/METADATA
python_SQLGrants-1.1.2.dist-info/WHEEL
python_SQLGrants-1.1.2.dist-info/top_level.txt
python_SQLGrants-1.1.2.dist-info/RECORD
