Metadata-Version: 2.1
Name: python-SQLGrants
Version: 1.1.2
Summary: Grants processing library
Home-page: https://github.com/painassasin/sqlgrants
Author: attr: sqlgrants.__author__
Author-email: painassasin@icloud.com
License: MIT
Platform: any
Classifier: Programming Language :: Python :: 3
Classifier: License :: OSI Approved :: MIT License
Classifier: Operating System :: OS Independent
Requires-Python: >=3.8
Requires-Dist: SQLAlchemy (>=1.4)
Requires-Dist: mysql-connector-python (>=8.0)
